emojidb/__init__.py
emojidb/cache.py
emojidb/client.py
emojidb/test/__init__.py
emojidb/test/test_client.py
emojidb_client-1.1.0.dist-info/METADATA
emojidb_client-1.1.0.dist-info/WHEEL
emojidb_client-1.1.0.dist-info/RECORD
