Metadata-Version: 2.4
Name: emojidb-client
Version: 1.1.0
Summary: Simple python wrapper for emojidb.com
Project-URL: Homepage, https://github.com/yedhrab/emojidb-python
Project-URL: Repository, https://github.com/yedhrab/emojidb-python
Project-URL: Issues, https://github.com/yedhrab/emojidb-python/issues
Project-URL: Changelog, https://github.com/yedhrab/emojidb-python/releases
Author-email: Yunus Emre Ak <yemreak.com@gmail.com>
Keywords: emoji,emojidb,emojidb-client,emojidb-client-python,emojidb.com
Classifier: Development Status :: 5 - Production/Stable
Classifier: Intended Audience :: Developers
Classifier: License :: OSI Approved :: Apache Software License
Classifier: Operating System :: OS Independent
Classifier: Programming Language :: Python :: 3.9
Classifier: Programming Language :: Python :: 3.10
Classifier: Programming Language :: Python :: 3.11
Classifier: Topic :: Utilities
Requires-Python: >=3.9.6
Requires-Dist: aiohttp==3.8.4
Requires-Dist: beautifulsoup4==4.12.2
Requires-Dist: easy-requests~=1.1.2
Requires-Dist: platformdirs~=4.4.0
Provides-Extra: dev
Requires-Dist: autoflake==2.0.2; extra == 'dev'
Requires-Dist: black==23.3.0; extra == 'dev'
Requires-Dist: pytest-asyncio==0.21.0; extra == 'dev'
Requires-Dist: pytest==7.3.0; extra == 'dev'
